MANIFEST.in
README.md
setup.py
getthat/__init__.py
getthat.egg-info/PKG-INFO
getthat.egg-info/SOURCES.txt
getthat.egg-info/dependency_links.txt
getthat.egg-info/top_level.txt
sample/sample.py