Metadata-Version: 2.1
Name: getthat
Version: 0.0.2
Summary: getthat i dont care if i don't have it.(pip3 install if modulenotfound)
Home-page: https://github.com/eaybek/getthat
Author: Erdem Aybek
Author-email: eaybek@gmail.com
License: UNKNOWN
Platform: UNKNOWN
Classifier: Programming Language :: Python :: 3
Classifier: License :: OSI Approved :: MIT License
Classifier: Operating System :: POSIX :: Linux
Classifier: Development Status :: 1 - Planning
Requires-Python: >=3.6
